aleatora/__init__.py
aleatora/audio.py
aleatora/chord.py
aleatora/fauxdot.py
aleatora/filters.py
aleatora/midi.py
aleatora/net.py
aleatora/plugins.py
aleatora/profile.py
aleatora/speech.py
aleatora/stk.py
aleatora/wav.py
aleatora/streams/__init__.py
aleatora/streams/audio.py
aleatora/streams/core.py
aleatora-0.2.1.dist-info/LICENSE
aleatora-0.2.1.dist-info/METADATA
aleatora-0.2.1.dist-info/WHEEL
aleatora-0.2.1.dist-info/top_level.txt
aleatora-0.2.1.dist-info/RECORD
