Metadata-Version: 2.1
Name: aleatora
Version: 0.2.1
Summary: Compose music with streams.
Home-page: https://github.com/ijc8/aleatora
Author: Ian Clester
Author-email: ijc@ijc8.me
Project-URL: Bug Tracker, https://github.com/ijc8/aleatora/issues
Classifier: Programming Language :: Python :: 3
Classifier: License :: OSI Approved :: GNU General Public License v3 (GPLv3)
Classifier: Topic :: Artistic Software
Classifier: Topic :: Multimedia :: Sound/Audio
Classifier: Topic :: Multimedia :: Sound/Audio :: Editors
Classifier: Topic :: Multimedia :: Sound/Audio :: MIDI
Classifier: Topic :: Multimedia :: Sound/Audio :: Mixers
Classifier: Topic :: Multimedia :: Sound/Audio :: Sound Synthesis
Classifier: Operating System :: OS Independent
Classifier: Development Status :: 3 - Alpha
Requires-Python: >=3.6
License-File: LICENSE
Requires-Dist: mido
Requires-Dist: numpy
Requires-Dist: oscpy
Requires-Dist: sounddevice
Provides-Extra: all
Requires-Dist: gtts ; extra == 'all'
Requires-Dist: streamp3 (~=0.1.7) ; extra == 'all'
Requires-Dist: FoxDotPatterns (~=0.1.0) ; extra == 'all'
Requires-Dist: popsicle (~=0.0.9) ; extra == 'all'
Requires-Dist: pyFluidSynth (==1.3.0) ; extra == 'all'
Requires-Dist: cppyy (~=2.3.1) ; extra == 'all'
Requires-Dist: ffmpeg-python (~=0.2.0) ; extra == 'all'
Provides-Extra: foxdot
Requires-Dist: FoxDotPatterns (~=0.1.0) ; extra == 'foxdot'
Provides-Extra: plugins
Requires-Dist: popsicle (~=0.0.9) ; extra == 'plugins'
Provides-Extra: rivalium
Requires-Dist: ffmpeg-python (~=0.2.0) ; extra == 'rivalium'
Provides-Extra: soundfont
Requires-Dist: pyFluidSynth (==1.3.0) ; extra == 'soundfont'
Provides-Extra: speech
Requires-Dist: gtts ; extra == 'speech'
Requires-Dist: streamp3 (~=0.1.7) ; extra == 'speech'
Provides-Extra: stk
Requires-Dist: cppyy (~=2.3.1) ; extra == 'stk'
